setup.py
RPiShift/__init__.py
RPiShift.egg-info/PKG-INFO
RPiShift.egg-info/SOURCES.txt
RPiShift.egg-info/dependency_links.txt
RPiShift.egg-info/top_level.txt