Metadata-Version: 1.1
Name: RPiShift
Version: 0.2.0
Summary: A module for interfacing a 595 shift register with the Raspberry Pi
Home-page: http://github.com/kneitinger/RPiShift
Author: Kyle J. Kneitinger
Author-email: kylejkneitinger@gmail.com
License: GPLv2
Keywords: raspberry pi 595 shift register electronics
Platform: UNKNOWN
Classifier: Development Status :: 3 - Alpha
Classifier: Environment :: Other Environment
Classifier: License :: OSI Approved :: GNU General Public License v2 (GPLv2)
Classifier: Operating System :: POSIX :: Linux
Classifier: Programming Language :: Python
Classifier: Topic :: Software Development :: Libraries :: Python Modules
